{
    "Id": "f65d15043fb24245948b4bad35418b51",
    "RecognitionStatus": "Success",
    "Offset": 4800000,
    "Duration": 9100000,
    "Channel": 0,
    "DisplayText": "Welcome.",
    "SNR": 20.453552,
    "NBest": [
        {
            "Confidence": 0.93153626,
            "Lexical": "welcome",
            "ITN": "welcome",
            "MaskedITN": "welcome",
            "Display": "Welcome.",
            "PronunciationAssessment": {
                "AccuracyScore": 8.0,
                "FluencyScore": 100.0,
                "ProsodyScore": 87.8,
                "CompletenessScore": 8.0,
                "PronScore": 42.4
            },
            "Words": [
                {
                    "Word": "welcome",
                    "Offset": 4800000,
                    "Duration": 9100000,
                    "PronunciationAssessment": {
                        "AccuracyScore": 94.0,
                        "ErrorType": "None",
                        "Feedback": {
                            "Prosody": {
                                "Break": {
                                    "ErrorTypes": [
                                        "None"
                                    ],
                                    "BreakLength": 0
                                },
                                "Intonation": {
                                    "ErrorTypes": [],
                                    "Monotone": {
                                        "SyllablePitchDeltaConfidence": 0.38828078
                                    }
                                }
                            }
                        }
                    },
                    "Syllables": [
                        {
                            "Syllable": "wɛl",
                            "Grapheme": "wel",
                            "PronunciationAssessment": {
                                "AccuracyScore": 80.0
                            },
                            "Offset": 4800000,
                            "Duration": 4500000
                        },
                        {
                            "Syllable": "kəm",
                            "Grapheme": "come",
                            "PronunciationAssessment": {
                                "AccuracyScore": 90.0
                            },
                            "Offset": 9400000,
                            "Duration": 4500000
                        }
                    ],
                    "Phonemes": [
                        {
                            "Phoneme": "w",
                            "PronunciationAssessment": {
                                "AccuracyScore": 69.0
                            },
                            "Offset": 4800000,
                            "Duration": 2900000
                        },
                        {
                            "Phoneme": "ɛ",
                            "PronunciationAssessment": {
                                "AccuracyScore": 100.0
                            },
                            "Offset": 7800000,
                            "Duration": 700000
                        },
                        {
                            "Phoneme": "l",
                            "PronunciationAssessment": {
                                "AccuracyScore": 100.0
                            },
                            "Offset": 8600000,
                            "Duration": 700000
                        },
                        {
                            "Phoneme": "k",
                            "PronunciationAssessment": {
                                "AccuracyScore": 100.0
                            },
                            "Offset": 9400000,
                            "Duration": 700000
                        },
                        {
                            "Phoneme": "ə",
                            "PronunciationAssessment": {
                                "AccuracyScore": 100.0
                            },
                            "Offset": 10200000,
                            "Duration": 700000
                        },
                        {
                            "Phoneme": "m",
                            "PronunciationAssessment": {
                                "AccuracyScore": 85.0
                            },
                            "Offset": 11000000,
                            "Duration": 2900000
                        }
                    ]
                },
                {
                    "Word": "I'm",
                    "PronunciationAssessment": {
                        "ErrorType": "Omission"
                    },
                    "Phonemes": []
                },
                {
                    "Word": "your",
                    "PronunciationAssessment": {
                        "ErrorType": "Omission"
                    },
                    "Phonemes": []
                },
                {
                    "Word": "English",
                    "PronunciationAssessment": {
                        "ErrorType": "Omission"
                    },
                    "Phonemes": []
                },
                {
                    "Word": "pronunciation",
                    "PronunciationAssessment": {
                        "ErrorType": "Omission"
                    },
                    "Phonemes": []
                },
                {
                    "Word": "trainer",
                    "PronunciationAssessment": {
                        "ErrorType": "Omission"
                    },
                    "Phonemes": []
                },
                {
                    "Word": "Let's",
                    "PronunciationAssessment": {
                        "ErrorType": "Omission"
                    },
                    "Phonemes": []
                },
                {
                    "Word": "have",
                    "PronunciationAssessment": {
                        "ErrorType": "Omission"
                    },
                    "Phonemes": []
                },
                {
                    "Word": "a",
                    "PronunciationAssessment": {
                        "ErrorType": "Omission"
                    },
                    "Phonemes": []
                },
                {
                    "Word": "great",
                    "PronunciationAssessment": {
                        "ErrorType": "Omission"
                    },
                    "Phonemes": []
                },
                {
                    "Word": "time",
                    "PronunciationAssessment": {
                        "ErrorType": "Omission"
                    },
                    "Phonemes": []
                },
                {
                    "Word": "together",
                    "PronunciationAssessment": {
                        "ErrorType": "Omission"
                    },
                    "Phonemes": []
                }
            ]
        }
    ]
}